pyspex/__init__.py
pyspex/binning_tables.py
pyspex/ccsds_io.py
pyspex/dem_io.py
pyspex/egse_db.py
pyspex/hkt_io.py
pyspex/l1a_io.py
pyspex/lv0_lib.py
pyspex/lv1_gse.py
pyspex/ogse_db.py
pyspex/ogse_dolp.py
pyspex/ogse_grande.py
pyspex/ogse_helios.py
pyspex/ogse_laser.py
pyspex/tif_io.py
pyspex/tlm.py
pyspex/Data/119871-1-1 Full Power 1nm data.xls
pyspex/Data/binning_tables.nc
pyspex/Data/h5_global_attrs.yaml
pyspex/Data/h5_level_1a.yaml
pyspex/Data/h5_nomhk_tm.yaml
pyspex/Data/h5_science_hk.yaml
pyspex/Data/logger_setup.yaml
pyspex/Data/tai-utc.dat
pyspex/gen_l1a/__init__.py
pyspex/gen_l1a/argparse_gen_l1a.py
pyspex/gen_l1a/cli.py
pyspex/gen_l1a/l1a.py
pyspex/lib/__init__.py
pyspex/lib/attrs_def.py
pyspex/lib/ccsds_hdr.py
pyspex/lib/hk_tlm.py
pyspex/lib/l1a_def.py
pyspex/lib/leap_sec.py
pyspex/lib/logger.py
pyspex/lib/sci_tlm.py
pyspex/lib/tlm_utils.py
pyspex/lib/tmtc_def.py
pyspex/scripts/spx1_add_egse2l1a.py
pyspex/scripts/spx1_add_ogse2l1a.py
pyspex/scripts/spx1_ccsds2l1a.py
pyspex/scripts/spx1_dem2l1a.py
pyspex/scripts/spx1_l1a_select.py
pyspex/scripts/spx1_quicklook_lite.py
pyspex/scripts/spx1_tif2l1a.py
pyspex-1.4.18.dist-info/METADATA
pyspex-1.4.18.dist-info/WHEEL
pyspex-1.4.18.dist-info/entry_points.txt
pyspex-1.4.18.dist-info/licenses/LICENSE
pyspex-1.4.18.dist-info/RECORD
