Metadata-Version: 2.4
Name: pyspex
Version: 1.4.18
Summary: Software package to handle SPEXone Level-0 and Level-1 data
Project-URL: Homepage, https://github.com/rmvanhees/pyspex
Project-URL: Source, https://github.com/rmvanhees/pyspex
Project-URL: Issues, https://github.com/rmvanhees/pyspex/issues
Project-URL: Documentation, https://pyspex.readthedocs.io/en/stable/
Author-email: Richard van Hees <r.m.van.hees@sron.nl>
License-Expression: BSD-3-Clause
License-File: LICENSE
Classifier: Development Status :: 5 - Production/Stable
Classifier: Intended Audience :: Developers
Classifier: Intended Audience :: Science/Research
Classifier: Operating System :: OS Independent
Classifier: Programming Language :: Python :: 3 :: Only
Classifier: Programming Language :: Python :: 3.8
Classifier: Programming Language :: Python :: 3.9
Classifier: Programming Language :: Python :: 3.10
Classifier: Programming Language :: Python :: 3.11
Classifier: Programming Language :: Python :: 3.12
Classifier: Programming Language :: Python :: 3.13
Classifier: Programming Language :: Python :: 3.14
Classifier: Topic :: Scientific/Engineering :: Atmospheric Science
Requires-Python: >=3.8
Requires-Dist: h5py>=3.9
Requires-Dist: h5yaml>=0.1.0; python_version >= '3.10'
Requires-Dist: julian
Requires-Dist: netcdf4>=1.7
Requires-Dist: numpy>=1.19; python_version < '3.10'
Requires-Dist: numpy>=2.0; python_version >= '3.10'
Requires-Dist: openpyxl>=3.0
Requires-Dist: pyxarr>=0.3.0; python_version >= '3.10'
Requires-Dist: pyyaml>=6.0
Requires-Dist: typing-extensions; python_version < '3.11'
Requires-Dist: xarray>=2024
